elkai/types.py
elkai/utils.py
elkai/_elkai.so
elkai/_elkai.c
elkai/__init__.py
elkai/deprecated.py
elkai-2.0.1.dist-info/METADATA
elkai-2.0.1.dist-info/entry_points.txt
elkai-2.0.1.dist-info/RECORD
elkai-2.0.1.dist-info/WHEEL
