Metadata-Version: 2.1
Name: elkai
Version: 2.0.1
Summary: elkai is a Python library for solving travelling salesman problems (TSP) based on LKH 3
Keywords: tsp travelling salesman problem solver atsp salesman travelling problem
Author: Filip Dimitrovski
License: elkai License
Requires-Python: >=3.7
